odoo/addons/privacy_partner_to_be_forgotten/README.rst
odoo/addons/privacy_partner_to_be_forgotten/__init__.py
odoo/addons/privacy_partner_to_be_forgotten/__manifest__.py
odoo/addons/privacy_partner_to_be_forgotten/demo/demo_partner_anonymize_data.xml
odoo/addons/privacy_partner_to_be_forgotten/i18n/it.po
odoo/addons/privacy_partner_to_be_forgotten/i18n/privacy_partner_to_be_forgotten.pot
odoo/addons/privacy_partner_to_be_forgotten/models/__init__.py
odoo/addons/privacy_partner_to_be_forgotten/models/res_partner.py
odoo/addons/privacy_partner_to_be_forgotten/readme/CONFIGURE.md
odoo/addons/privacy_partner_to_be_forgotten/readme/CONTEXT.md
odoo/addons/privacy_partner_to_be_forgotten/readme/CONTRIBUTORS.md
odoo/addons/privacy_partner_to_be_forgotten/readme/DESCRIPTION.md
odoo/addons/privacy_partner_to_be_forgotten/readme/HISTORY.md
odoo/addons/privacy_partner_to_be_forgotten/readme/USAGE.md
odoo/addons/privacy_partner_to_be_forgotten/security/ir.model.access.csv
odoo/addons/privacy_partner_to_be_forgotten/security/security.xml
odoo/addons/privacy_partner_to_be_forgotten/static/description/icon.png
odoo/addons/privacy_partner_to_be_forgotten/static/description/index.html
odoo/addons/privacy_partner_to_be_forgotten/tests/__init__.py
odoo/addons/privacy_partner_to_be_forgotten/tests/test_partner_anonymize.py
odoo/addons/privacy_partner_to_be_forgotten/views/res_partner_views.xml
odoo/addons/privacy_partner_to_be_forgotten/wizards/__init__.py
odoo/addons/privacy_partner_to_be_forgotten/wizards/partner_anonymize_wizard.py
odoo/addons/privacy_partner_to_be_forgotten/wizards/partner_anonymize_wizard_views.xml
odoo_addon_privacy_partner_to_be_forgotten-18.0.1.0.0.3.dist-info/METADATA
odoo_addon_privacy_partner_to_be_forgotten-18.0.1.0.0.3.dist-info/WHEEL
odoo_addon_privacy_partner_to_be_forgotten-18.0.1.0.0.3.dist-info/top_level.txt
odoo_addon_privacy_partner_to_be_forgotten-18.0.1.0.0.3.dist-info/RECORD
